advik/__init__.py
advik/__main__.py
advik/sections/1-about
advik/sections/2-experience
advik/sections/3-projects
advik/sections/4-education
advik/sections/5-skills
advik/utils.py
advik-0.1.6.dist-info/METADATA
advik-0.1.6.dist-info/WHEEL
advik-0.1.6.dist-info/entry_points.txt
advik-0.1.6.dist-info/RECORD
